odoo/addons/sale_resource_booking/README.rst
odoo/addons/sale_resource_booking/__init__.py
odoo/addons/sale_resource_booking/__manifest__.py
odoo/addons/sale_resource_booking/i18n/es.po
odoo/addons/sale_resource_booking/i18n/fr.po
odoo/addons/sale_resource_booking/i18n/fr_CH.po
odoo/addons/sale_resource_booking/i18n/it.po
odoo/addons/sale_resource_booking/i18n/sale_resource_booking.pot
odoo/addons/sale_resource_booking/models/__init__.py
odoo/addons/sale_resource_booking/models/product_template.py
odoo/addons/sale_resource_booking/models/resource_booking.py
odoo/addons/sale_resource_booking/models/resource_booking_type.py
odoo/addons/sale_resource_booking/models/sale_order.py
odoo/addons/sale_resource_booking/models/sale_order_line.py
odoo/addons/sale_resource_booking/readme/CONFIGURE.md
odoo/addons/sale_resource_booking/readme/CONTRIBUTORS.md
odoo/addons/sale_resource_booking/readme/DESCRIPTION.md
odoo/addons/sale_resource_booking/readme/INSTALL.md
odoo/addons/sale_resource_booking/readme/USAGE.md
odoo/addons/sale_resource_booking/security/ir.model.access.csv
odoo/addons/sale_resource_booking/static/description/icon.png
odoo/addons/sale_resource_booking/static/description/index.html
odoo/addons/sale_resource_booking/tests/__init__.py
odoo/addons/sale_resource_booking/tests/test_sale_resource_booking.py
odoo/addons/sale_resource_booking/views/product_template_views.xml
odoo/addons/sale_resource_booking/views/resource_booking_type_views.xml
odoo/addons/sale_resource_booking/views/resource_booking_views.xml
odoo/addons/sale_resource_booking/views/sale_order_views.xml
odoo/addons/sale_resource_booking/wizards/__init__.py
odoo/addons/sale_resource_booking/wizards/resource_booking_sale.py
odoo/addons/sale_resource_booking/wizards/resource_booking_sale_views.xml
odoo/addons/sale_resource_booking/wizards/sale_order_booking_confirm.py
odoo/addons/sale_resource_booking/wizards/sale_order_booking_confirm_views.xml
odoo_addon_sale_resource_booking-17.0.1.0.0.4.dist-info/METADATA
odoo_addon_sale_resource_booking-17.0.1.0.0.4.dist-info/WHEEL
odoo_addon_sale_resource_booking-17.0.1.0.0.4.dist-info/top_level.txt
odoo_addon_sale_resource_booking-17.0.1.0.0.4.dist-info/RECORD
